{
    "company_code": "MMS",
    "financial_data": [
        {
            "date": "2010-09-30",
            "Year": 2,
            "ebitda": 34.882,
            "operating expenses": 182326000.0,
            "cost of-sales": 151.422,
            "net income": 21.713,
            "gross profit-on-sales": 61094000.0,
            "ebit": 30190000.0,
            "operating profit": 30190000.0,
            "pre tax-profit": 27.783
        },
        {
            "date": "2010-12-31",
            "Year": 3,
            "ebitda": 32.524,
            "operating expenses": 186822000.0,
            "cost of-sales": 158.155,
            "net income": 17.482,
            "gross profit-on-sales": 55959000.0,
            "ebit": 27292000.0,
            "operating profit": 27292000.0,
            "pre tax-profit": 27.783
        },
        {
            "date": "2011-03-31",
            "Year": 4,
            "ebitda": 35.045,
            "operating expenses": 197622000.0,
            "cost of-sales": 164.05,
            "net income": 18.219,
            "gross profit-on-sales": 63066000.0,
            "ebit": 29494000.0,
            "operating profit": 29494000.0,
            "pre tax-profit": 30.413
        },
        {
            "date": "2011-06-30",
            "Year": 5,
            "ebitda": 36.836,
            "operating expenses": 207517000.0,
            "cost of-sales": 171.897,
            "net income": 19.892,
            "gross profit-on-sales": 66399000.0,
            "ebit": 31140000.0,
            "operating profit": 30779000.0,
            "pre tax-profit": 31.74
        },
        {
            "date": "2011-09-30",
            "Year": 6,
            "ebitda": 40.033,
            "operating expenses": 215271000.0,
            "cost of-sales": 181.88,
            "net income": 25.575,
            "gross profit-on-sales": 68227000.0,
            "ebit": 33667000.0,
            "operating profit": 34836000.0,
            "pre tax-profit": 37.129
        },
        {
            "date": "2011-12-31",
            "Year": 7,
            "ebitda": 33.202,
            "operating expenses": 212698000.0,
            "cost of-sales": 179.756,
            "net income": 17.704,
            "gross profit-on-sales": 59847000.0,
            "ebit": 27091000.0,
            "operating profit": 26905000.0,
            "pre tax-profit": 28.195
        },
        {
            "date": "2012-03-31",
            "Year": 8,
            "ebitda": 32.241,
            "operating expenses": 216054000.0,
            "cost of-sales": 178.686,
            "net income": 14.273,
            "gross profit-on-sales": 64766000.0,
            "ebit": 26807000.0,
            "operating profit": 27398000.0,
            "pre tax-profit": 28.813
        },
        {
            "date": "2012-06-30",
            "Year": 9,
            "ebitda": 41.792,
            "operating expenses": 233054000.0,
            "cost of-sales": 187.652,
            "net income": 20.485,
            "gross profit-on-sales": 78701000.0,
            "ebit": 34824000.0,
            "operating profit": 33299000.0,
            "pre tax-profit": 28.813
        },
        {
            "date": "2012-09-30",
            "Year": 10,
            "ebitda": 49.766,
            "operating expenses": 260763000.0,
            "cost of-sales": 216.107,
            "net income": 23.671,
            "gross profit-on-sales": 84629000.0,
            "ebit": 41819000.0,
            "operating profit": 39973000.0,
            "pre tax-profit": 28.813
        },
        {
            "date": "2012-12-31",
            "Year": 11,
            "ebitda": 44.283,
            "operating expenses": 252248000.0,
            "cost of-sales": 209.736,
            "net income": 21.316,
            "gross profit-on-sales": 76530000.0,
            "ebit": 34308000.0,
            "operating profit": 34018000.0,
            "pre tax-profit": 35.414
        },
        {
            "date": "2013-03-31",
            "Year": 12,
            "ebitda": 58.71,
            "operating expenses": 275616000.0,
            "cost of-sales": 228.907,
            "net income": 31.689,
            "gross profit-on-sales": 97444000.0,
            "ebit": 50751000.0,
            "operating profit": 50735000.0,
            "pre tax-profit": 40.472
        },
        {
            "date": "2013-06-30",
            "Year": 13,
            "ebitda": 53.208,
            "operating expenses": 289936000.0,
            "cost of-sales": 239.763,
            "net income": 28.1,
            "gross profit-on-sales": 94560000.0,
            "ebit": 45379000.0,
            "operating profit": 44387000.0,
            "pre tax-profit": 46.077
        },
        {
            "date": "2013-09-30",
            "Year": 14,
            "ebitda": 68.597,
            "operating expenses": 328324000.0,
            "cost of-sales": 266.84,
            "net income": 35.626,
            "gross profit-on-sales": 117499000.0,
            "ebit": 56885000.0,
            "operating profit": 56015000.0,
            "pre tax-profit": 58.143
        },
        {
            "date": "2013-12-31",
            "Year": 15,
            "ebitda": 65.366,
            "operating expenses": 353295000.0,
            "cost of-sales": 300.676,
            "net income": 33.859,
            "gross profit-on-sales": 105916000.0,
            "ebit": 53297000.0,
            "operating profit": 53297000.0,
            "pre tax-profit": 54.034
        },
        {
            "date": "2014-03-31",
            "Year": 16,
            "ebitda": 77.317,
            "operating expenses": 374035000.0,
            "cost of-sales": 318.343,
            "net income": 41.207,
            "gross profit-on-sales": 120672000.0,
            "ebit": 65580000.0,
            "operating profit": 64980000.0,
            "pre tax-profit": 65.726
        },
        {
            "date": "2014-06-30",
            "Year": 17,
            "ebitda": 70.619,
            "operating expenses": 364676000.0,
            "cost of-sales": 307.296,
            "net income": 34.138,
            "gross profit-on-sales": 112603000.0,
            "ebit": 55223000.0,
            "operating profit": 55223000.0,
            "pre tax-profit": 55.267
        },
        {
            "date": "2014-09-30",
            "Year": 18,
            "ebitda": 63.929,
            "operating expenses": 383597000.0,
            "cost of-sales": 322.474,
            "net income": 36.236,
            "gross profit-on-sales": 112932000.0,
            "ebit": 51209000.0,
            "operating profit": 51809000.0,
            "pre tax-profit": 52.566
        },
        {
            "date": "2014-12-31",
            "Year": 19,
            "ebitda": 77.672,
            "operating expenses": 401812000.0,
            "cost of-sales": 347.776,
            "net income": 41.861,
            "gross profit-on-sales": 119267000.0,
            "ebit": 65231000.0,
            "operating profit": 65231000.0,
            "pre tax-profit": 66.132
        },
        {
            "date": "2015-03-31",
            "Year": 20,
            "ebitda": 77.693,
            "operating expenses": 419787000.0,
            "cost of-sales": 357.449,
            "net income": 38.808,
            "gross profit-on-sales": 124345000.0,
            "ebit": 64121000.0,
            "operating profit": 62007000.0,
            "pre tax-profit": 63.74
        },
        {
            "date": "2015-06-30",
            "Year": 21,
            "ebitda": 90.737,
            "operating expenses": 501234000.0,
            "cost of-sales": 428.503,
            "net income": 41.666,
            "gross profit-on-sales": 143798000.0,
            "ebit": 73526000.0,
            "operating profit": 71067000.0,
            "pre tax-profit": 72.845
        },
        {
            "date": "2015-09-30",
            "Year": 22,
            "ebitda": 74.097,
            "operating expenses": 517156000.0,
            "cost of-sales": 453.376,
            "net income": 35.438,
            "gross profit-on-sales": 125307000.0,
            "ebit": 61699000.0,
            "operating profit": 61527000.0,
            "pre tax-profit": 61.075
        },
        {
            "date": "2015-12-31",
            "Year": 23,
            "ebitda": 58.928,
            "operating expenses": 513936000.0,
            "cost of-sales": 446.507,
            "net income": 26.609,
            "gross profit-on-sales": 110215000.0,
            "ebit": 42832000.0,
            "operating profit": 42786000.0,
            "pre tax-profit": 42.882
        },
        {
            "date": "2016-03-31",
            "Year": 24,
            "ebitda": 94.603,
            "operating expenses": 528553000.0,
            "cost of-sales": 458.786,
            "net income": 48.785,
            "gross profit-on-sales": 147667000.0,
            "ebit": 78429000.0,
            "operating profit": 77900000.0,
            "pre tax-profit": 69.767
        },
        {
            "date": "2016-06-30",
            "Year": 25,
            "ebitda": 95.06,
            "operating expenses": 532485000.0,
            "cost of-sales": 465.715,
            "net income": 52.225,
            "gross profit-on-sales": 151379000.0,
            "ebit": 78156000.0,
            "operating profit": 84609000.0,
            "pre tax-profit": 77.189
        },
        {
            "date": "2016-09-30",
            "Year": 26,
            "ebitda": 103.745,
            "operating expenses": 541783000.0,
            "cost of-sales": 470.161,
            "net income": 50.743,
            "gross profit-on-sales": 152930000.0,
            "ebit": 81138000.0,
            "operating profit": 81308000.0,
            "pre tax-profit": 80.562
        },
        {
            "date": "2016-12-31",
            "Year": 27,
            "ebitda": 93.982,
            "operating expenses": 533788000.0,
            "cost of-sales": 462.746,
            "net income": 46.664,
            "gross profit-on-sales": 144818000.0,
            "ebit": 76018000.0,
            "operating profit": 73776000.0,
            "pre tax-profit": 73.19
        },
        {
            "date": "2017-03-31",
            "Year": 28,
            "ebitda": 99.126,
            "operating expenses": 541712000.0,
            "cost of-sales": 469.73,
            "net income": 52.515,
            "gross profit-on-sales": 152317000.0,
            "ebit": 80335000.0,
            "operating profit": 80335000.0,
            "pre tax-profit": 80.008
        },
        {
            "date": "2017-06-30",
            "Year": 29,
            "ebitda": 97.33,
            "operating expenses": 518636000.0,
            "cost of-sales": 448.258,
            "net income": 56.918,
            "gross profit-on-sales": 152189000.0,
            "ebit": 81161000.0,
            "operating profit": 81811000.0,
            "pre tax-profit": 82.659
        },
        {
            "date": "2017-09-30",
            "Year": 30,
            "ebitda": 92.726,
            "operating expenses": 543313000.0,
            "cost of-sales": 458.322,
            "net income": 53.329,
            "gross profit-on-sales": 162581000.0,
            "ebit": 77673000.0,
            "operating profit": 77590000.0,
            "pre tax-profit": 78.378
        },
        {
            "date": "2017-12-31",
            "Year": 31,
            "ebitda": 96.12,
            "operating expenses": 543465000.0,
            "cost of-sales": 471.188,
            "net income": 59.091,
            "gross profit-on-sales": 151960000.0,
            "ebit": 79683000.0,
            "operating profit": 79683000.0,
            "pre tax-profit": 79.802
        },
        {
            "date": "2018-03-31",
            "Year": 32,
            "ebitda": 89.599,
            "operating expenses": 541466000.0,
            "cost of-sales": 463.984,
            "net income": 55.492,
            "gross profit-on-sales": 148803000.0,
            "ebit": 73641000.0,
            "operating profit": 71321000.0,
            "pre tax-profit": 72.556
        },
        {
            "date": "2018-06-30",
            "Year": 33,
            "ebitda": 97.924,
            "operating expenses": 515284000.0,
            "cost of-sales": 443.171,
            "net income": 59.861,
            "gross profit-on-sales": 154684000.0,
            "ebit": 82571000.0,
            "operating profit": 82571000.0,
            "pre tax-profit": 84.735
        },
        {
            "date": "2018-09-30",
            "Year": 34,
            "ebitda": 77.385,
            "operating expenses": 496538000.0,
            "cost of-sales": 419.508,
            "net income": 46.307,
            "gross profit-on-sales": 138938000.0,
            "ebit": 62941000.0,
            "operating profit": 61908000.0,
            "pre tax-profit": 62.116
        },
        {
            "date": "2018-12-31",
            "Year": 35,
            "ebitda": 93.515,
            "operating expenses": 590483000.0,
            "cost of-sales": 505.354,
            "net income": 55.913,
            "gross profit-on-sales": 159265000.0,
            "ebit": 76826000.0,
            "operating profit": 74136000.0,
            "pre tax-profit": 75.556
        },
        {
            "date": "2019-03-31",
            "Year": 36,
            "ebitda": 102.656,
            "operating expenses": 654719000.0,
            "cost of-sales": 567.098,
            "net income": 61.924,
            "gross profit-on-sales": 169422000.0,
            "ebit": 81961000.0,
            "operating profit": 81801000.0,
            "pre tax-profit": 80.679
        },
        {
            "date": "2019-06-30",
            "Year": 37,
            "ebitda": 104.956,
            "operating expenses": 647116000.0,
            "cost of-sales": 556.463,
            "net income": 62.898,
            "gross profit-on-sales": 174247000.0,
            "ebit": 83726000.0,
            "operating profit": 83594000.0,
            "pre tax-profit": 83.73
        },
        {
            "date": "2019-09-30",
            "Year": 38,
            "ebitda": 104.129,
            "operating expenses": 677390000.0,
            "cost of-sales": 586.716,
            "net income": 60.089,
            "gross profit-on-sales": 168250000.0,
            "ebit": 77285000.0,
            "operating profit": 77576000.0,
            "pre tax-profit": 77.355
        },
        {
            "date": "2019-12-31",
            "Year": 39,
            "ebitda": 103.541,
            "operating expenses": 739094000.0,
            "cost of-sales": 642.779,
            "net income": 58.734,
            "gross profit-on-sales": 175450000.0,
            "ebit": 79135000.0,
            "operating profit": 79135000.0,
            "pre tax-profit": 79.37
        },
        {
            "date": "2020-03-31",
            "Year": 40,
            "ebitda": 65.522,
            "operating expenses": 780824000.0,
            "cost of-sales": 665.037,
            "net income": 27.65,
            "gross profit-on-sales": 153098000.0,
            "ebit": 40688000.0,
            "operating profit": 37311000.0,
            "pre tax-profit": 37.419
        },
        {
            "date": "2020-06-30",
            "Year": 41,
            "ebitda": 111.378,
            "operating expenses": 814028000.0,
            "cost of-sales": 715.734,
            "net income": 64.464,
            "gross profit-on-sales": 185603000.0,
            "ebit": 86388000.0,
            "operating profit": 87309000.0,
            "pre tax-profit": 86.022
        },
        {
            "date": "2020-09-30",
            "Year": 42,
            "ebitda": 112.101,
            "operating expenses": 839313000.0,
            "cost of-sales": 726.985,
            "net income": 63.661,
            "gross profit-on-sales": 196851000.0,
            "ebit": 86170000.0,
            "operating profit": 84523000.0,
            "pre tax-profit": 84.251
        },
        {
            "date": "2020-12-31",
            "Year": 43,
            "ebitda": 107.778,
            "operating expenses": 857982000.0,
            "cost of-sales": 739.499,
            "net income": 64.077,
            "gross profit-on-sales": 206055000.0,
            "ebit": 89445000.0,
            "operating profit": 87572000.0,
            "pre tax-profit": 86.591
        },
        {
            "date": "2021-03-31",
            "Year": 44,
            "ebitda": 131.732,
            "operating expenses": 846094000.0,
            "cost of-sales": 728.622,
            "net income": 80.614,
            "gross profit-on-sales": 230658000.0,
            "ebit": 115644000.0,
            "operating profit": 113186000.0,
            "pre tax-profit": 111.91
        },
        {
            "date": "2021-06-30",
            "Year": 45,
            "ebitda": 167.822,
            "operating expenses": 1103925000.0,
            "cost of-sales": 951.664,
            "net income": 94.495,
            "gross profit-on-sales": 291856000.0,
            "ebit": 144861000.0,
            "operating profit": 139595000.0,
            "pre tax-profit": 128.219
        },
        {
            "date": "2021-09-30",
            "Year": 46,
            "ebitda": 115.236,
            "operating expenses": 1037954000.0,
            "cost of-sales": 887.725,
            "net income": 52.014,
            "gross profit-on-sales": 218406000.0,
            "ebit": 81900000.0,
            "operating profit": 68177000.0,
            "pre tax-profit": 56.961
        },
        {
            "date": "2021-12-31",
            "Year": 47,
            "ebitda": 117.789,
            "operating expenses": 1069347000.0,
            "cost of-sales": 922.721,
            "net income": 53.33,
            "gross profit-on-sales": 228155000.0,
            "ebit": 84019000.0,
            "operating profit": 81529000.0,
            "pre tax-profit": 71.58
        },
        {
            "date": "2022-03-31",
            "Year": 48,
            "ebitda": 108.153,
            "operating expenses": 1102038000.0,
            "cost of-sales": 948.875,
            "net income": 50.096,
            "gross profit-on-sales": 228451000.0,
            "ebit": 75463000.0,
            "operating profit": 75288000.0,
            "pre tax-profit": 66.565
        },
        {
            "date": "2022-06-30",
            "Year": 49,
            "ebitda": 87.88,
            "operating expenses": 1071228000.0,
            "cost of-sales": 915.564,
            "net income": 31.335,
            "gross profit-on-sales": 210221000.0,
            "ebit": 56514000.0,
            "operating profit": 54557000.0,
            "pre tax-profit": 41.269
        },
        {
            "date": "2022-09-30",
            "Year": 50,
            "ebitda": 136.647,
            "operating expenses": 1062507000.0,
            "cost of-sales": 904.048,
            "net income": 69.067,
            "gross profit-on-sales": 272983000.0,
            "ebit": 101678000.0,
            "operating profit": 114524000.0,
            "pre tax-profit": 97.684
        },
        {
            "date": "2022-12-31",
            "Year": 51,
            "ebitda": 111.969,
            "operating expenses": 1174469000.0,
            "cost of-sales": 1004.499,
            "net income": 39.995,
            "gross profit-on-sales": 244747000.0,
            "ebit": 76171000.0,
            "operating profit": 74777000.0,
            "pre tax-profit": 53.437
        },
        {
            "date": "2023-03-31",
            "Year": 52,
            "ebitda": 101.205,
            "operating expenses": 1144347000.0,
            "cost of-sales": 978.249,
            "net income": 31.788,
            "gross profit-on-sales": 228603000.0,
            "ebit": 63514000.0,
            "operating profit": 62505000.0,
            "pre tax-profit": 42.324
        },
        {
            "date": "2023-06-30",
            "Year": 53,
            "ebitda": 95.06,
            "operating expenses": 1130289000.0,
            "cost of-sales": 924.313,
            "net income": 30.863,
            "gross profit-on-sales": 264364000.0,
            "ebit": 60858000.0,
            "operating profit": 58388000.0,
            "pre tax-profit": 36.357
        },
        {
            "date": "2023-09-30",
            "Year": 54,
            "ebitda": 140.749,
            "operating expenses": 1160829000.0,
            "cost of-sales": 969.059,
            "net income": 59.146,
            "gross profit-on-sales": 290894000.0,
            "ebit": 99124000.0,
            "operating profit": 99124000.0,
            "pre tax-profit": 78.175
        },
        {
            "date": "2023-12-31",
            "Year": 55,
            "ebitda": 142.012,
            "operating expenses": 1219530000.0,
            "cost of-sales": 1026.99,
            "net income": 64.15,
            "gross profit-on-sales": 300050000.0,
            "ebit": 107510000.0,
            "operating profit": 107510000.0,
            "pre tax-profit": 85.515
        },
        {
            "date": "2024-03-31",
            "Year": 56,
            "ebitda": 158.162,
            "operating expenses": 1220863000.0,
            "cost of-sales": 1030.768,
            "net income": 80.51,
            "gross profit-on-sales": 317589000.0,
            "ebit": 128316000.0,
            "operating profit": 127494000.0,
            "pre tax-profit": 107.95
        },
        {
            "date": "2024-06-30",
            "Year": 57,
            "ebitda": 172.002,
            "operating expenses": 1172830000.0,
            "cost of-sales": 982.62,
            "net income": 89.752,
            "gross profit-on-sales": 332314000.0,
            "ebit": 140930000.0,
            "operating profit": 141739000.0,
            "pre tax-profit": 120.375
        },
        {
            "date": "2024-09-30",
            "Year": 58,
            "ebitda": 144.605,
            "operating expenses": 1204110000.0,
            "cost of-sales": 1014.175,
            "net income": 72.5,
            "gross profit-on-sales": 301700000.0,
            "ebit": 111756000.0,
            "operating profit": 111760000.0,
            "pre tax-profit": 92.669
        }
    ]
}