{
    "company_code": "PH",
    "financial_data": [
        {
            "date": "2010-06-30",
            "Year": 0,
            "ebitda": 373.989,
            "operating expenses": 2494.31,
            "cost of-sales": 2114.19,
            "net income": 222.163,
            "gross profit-on-sales": 672.28,
            "ebit": 319.056,
            "operating profit": 292.16,
            "pre tax-profit": 292.162
        },
        {
            "date": "2010-09-30",
            "Year": 1,
            "ebitda": 449.052,
            "operating expenses": 2492.909,
            "cost of-sales": 2137.874,
            "net income": 247.171,
            "gross profit-on-sales": 691.399,
            "ebit": 364.066,
            "operating profit": 336.364,
            "pre tax-profit": 336.364
        },
        {
            "date": "2010-12-31",
            "Year": 2,
            "ebitda": 418.991,
            "operating expenses": 2560.414,
            "cost of-sales": 2195.728,
            "net income": 230.18,
            "gross profit-on-sales": 670.936,
            "ebit": 333.569,
            "operating profit": 306.25,
            "pre tax-profit": 306.25
        },
        {
            "date": "2011-03-31",
            "Year": 3,
            "ebitda": 502.756,
            "operating expenses": 2850.386,
            "cost of-sales": 2463.083,
            "net income": 279.589,
            "gross profit-on-sales": 777.02,
            "ebit": 419.646,
            "operating profit": 389.717,
            "pre tax-profit": 389.717
        },
        {
            "date": "2011-06-30",
            "Year": 4,
            "ebitda": 494.678,
            "operating expenses": 3028.44,
            "cost of-sales": 2590.772,
            "net income": 292.19,
            "gross profit-on-sales": 819.058,
            "ebit": 407.811,
            "operating profit": 381.39,
            "pre tax-profit": 381.39
        },
        {
            "date": "2011-09-30",
            "Year": 5,
            "ebitda": 525.665,
            "operating expenses": 2822.296,
            "cost of-sales": 2414.442,
            "net income": 297.018,
            "gross profit-on-sales": 819.439,
            "ebit": 440.833,
            "operating profit": 411.585,
            "pre tax-profit": 411.585
        },
        {
            "date": "2011-12-31",
            "Year": 6,
            "ebitda": 443.209,
            "operating expenses": 2767.885,
            "cost of-sales": 2381.322,
            "net income": 240.766,
            "gross profit-on-sales": 725.51,
            "ebit": 363.91,
            "operating profit": 338.947,
            "pre tax-profit": 338.947
        },
        {
            "date": "2012-03-31",
            "Year": 7,
            "ebitda": 506.737,
            "operating expenses": 2992.736,
            "cost of-sales": 2590.315,
            "net income": 312.074,
            "gross profit-on-sales": 803.248,
            "ebit": 426.465,
            "operating profit": 400.827,
            "pre tax-profit": 400.827
        },
        {
            "date": "2012-06-30",
            "Year": 8,
            "ebitda": 523.981,
            "operating expenses": 2986.327,
            "cost of-sales": 2572.258,
            "net income": 301.965,
            "gross profit-on-sales": 839.408,
            "ebit": 446.455,
            "operating profit": 425.339,
            "pre tax-profit": 425.339
        },
        {
            "date": "2012-09-30",
            "Year": 9,
            "ebitda": 443.63,
            "operating expenses": 2878.877,
            "cost of-sales": 2477.447,
            "net income": 239.741,
            "gross profit-on-sales": 737.488,
            "ebit": 362.458,
            "operating profit": 336.058,
            "pre tax-profit": 336.058
        },
        {
            "date": "2012-12-31",
            "Year": 10,
            "ebitda": 374.184,
            "operating expenses": 2802.866,
            "cost of-sales": 2419.874,
            "net income": 180.962,
            "gross profit-on-sales": 645.621,
            "ebit": 291.529,
            "operating profit": 262.629,
            "pre tax-profit": 262.629
        },
        {
            "date": "2013-03-31",
            "Year": 11,
            "ebitda": 450.299,
            "operating expenses": 2968.49,
            "cost of-sales": 2567.715,
            "net income": 256.56,
            "gross profit-on-sales": 739.326,
            "ebit": 363.552,
            "operating profit": 338.551,
            "pre tax-profit": 338.551
        },
        {
            "date": "2013-06-30",
            "Year": 12,
            "ebitda": 474.069,
            "operating expenses": 3054.47,
            "cost of-sales": 2615.291,
            "net income": 271.164,
            "gross profit-on-sales": 812.942,
            "ebit": 389.019,
            "operating profit": 373.763,
            "pre tax-profit": 373.763
        },
        {
            "date": "2013-09-30",
            "Year": 13,
            "ebitda": 442.951,
            "operating expenses": 2902.054,
            "cost of-sales": 2470.216,
            "net income": 244.316,
            "gross profit-on-sales": 755.928,
            "ebit": 357.371,
            "operating profit": 324.09,
            "pre tax-profit": 324.09
        },
        {
            "date": "2013-12-31",
            "Year": 14,
            "ebitda": 786.019,
            "operating expenses": 2610.69,
            "cost of-sales": 2410.92,
            "net income": 253.288,
            "gross profit-on-sales": 695.086,
            "ebit": 701.509,
            "operating profit": 495.316,
            "pre tax-profit": 431.852
        },
        {
            "date": "2014-03-31",
            "Year": 15,
            "ebitda": 493.025,
            "operating expenses": 3028.916,
            "cost of-sales": 2574.84,
            "net income": 242.406,
            "gross profit-on-sales": 783.566,
            "ebit": 409.965,
            "operating profit": 329.49,
            "pre tax-profit": 329.49
        },
        {
            "date": "2014-06-30",
            "Year": 16,
            "ebitda": 120.752,
            "operating expenses": 3117.591,
            "cost of-sales": 2668.676,
            "net income": 301.038,
            "gross profit-on-sales": 856.739,
            "ebit": 37.2,
            "operating profit": 407.824,
            "pre tax-profit": 407.824
        },
        {
            "date": "2014-09-30",
            "Year": 17,
            "ebitda": 507.128,
            "operating expenses": 2873.297,
            "cost of-sales": 2454.747,
            "net income": 280.089,
            "gross profit-on-sales": 815.185,
            "ebit": 425.36,
            "operating profit": 396.635,
            "pre tax-profit": 396.635
        },
        {
            "date": "2014-12-31",
            "Year": 18,
            "ebitda": 458.852,
            "operating expenses": 2791.727,
            "cost of-sales": 2396.095,
            "net income": 267.252,
            "gross profit-on-sales": 738.898,
            "ebit": 379.995,
            "operating profit": 343.266,
            "pre tax-profit": 349.716
        },
        {
            "date": "2015-03-31",
            "Year": 19,
            "ebitda": 508.226,
            "operating expenses": 2773.945,
            "cost of-sales": 2368.193,
            "net income": 285.345,
            "gross profit-on-sales": 794.118,
            "ebit": 431.619,
            "operating profit": 388.366,
            "pre tax-profit": 456.089
        },
        {
            "date": "2015-06-30",
            "Year": 20,
            "ebitda": 433.118,
            "operating expenses": 2840.535,
            "cost of-sales": 2416.791,
            "net income": 179.454,
            "gross profit-on-sales": 727.717,
            "ebit": 352.859,
            "operating profit": 303.973,
            "pre tax-profit": 326.021
        },
        {
            "date": "2015-09-30",
            "Year": 21,
            "ebitda": 411.535,
            "operating expenses": 2593.699,
            "cost of-sales": 2186.231,
            "net income": 194.978,
            "gross profit-on-sales": 683.117,
            "ebit": 333.313,
            "operating profit": 275.649,
            "pre tax-profit": 297.437
        },
        {
            "date": "2015-12-31",
            "Year": 22,
            "ebitda": 365.319,
            "operating expenses": 2475.71,
            "cost of-sales": 2122.366,
            "net income": 182.982,
            "gross profit-on-sales": 583.224,
            "ebit": 287.448,
            "operating profit": 229.88,
            "pre tax-profit": 264.68
        },
        {
            "date": "2016-03-31",
            "Year": 23,
            "ebitda": 409.501,
            "operating expenses": 2555.672,
            "cost of-sales": 2187.773,
            "net income": 187.084,
            "gross profit-on-sales": 640.892,
            "ebit": 333.817,
            "operating profit": 272.993,
            "pre tax-profit": 298.023
        },
        {
            "date": "2016-06-30",
            "Year": 24,
            "ebitda": 458.06,
            "operating expenses": 2620.944,
            "cost of-sales": 2250.817,
            "net income": 241.796,
            "gross profit-on-sales": 706.333,
            "ebit": 382.994,
            "operating profit": 336.206,
            "pre tax-profit": 361.23
        },
        {
            "date": "2016-09-30",
            "Year": 25,
            "ebitda": 412.471,
            "operating expenses": 2450.886,
            "cost of-sales": 2097.986,
            "net income": 210.129,
            "gross profit-on-sales": 645.145,
            "ebit": 337.138,
            "operating profit": 292.245,
            "pre tax-profit": 302.99
        },
        {
            "date": "2016-12-31",
            "Year": 26,
            "ebitda": 435.815,
            "operating expenses": 2350.082,
            "cost of-sales": 2037.878,
            "net income": 241.305,
            "gross profit-on-sales": 632.926,
            "ebit": 362.063,
            "operating profit": 320.722,
            "pre tax-profit": 344.719
        },
        {
            "date": "2017-03-31",
            "Year": 27,
            "ebitda": 460.896,
            "operating expenses": 2804.076,
            "cost of-sales": 2373.448,
            "net income": 238.673,
            "gross profit-on-sales": 745.691,
            "ebit": 373.438,
            "operating profit": 315.063,
            "pre tax-profit": 357.607
        },
        {
            "date": "2017-06-30",
            "Year": 28,
            "ebitda": 550.26,
            "operating expenses": 3095.627,
            "cost of-sales": 2643.718,
            "net income": 293.305,
            "gross profit-on-sales": 852.52,
            "ebit": 431.574,
            "operating profit": 400.611,
            "pre tax-profit": 453.446
        },
        {
            "date": "2017-09-30",
            "Year": 29,
            "ebitda": 578.69,
            "operating expenses": 2990.349,
            "cost of-sales": 2523.763,
            "net income": 285.397,
            "gross profit-on-sales": 840.888,
            "ebit": 462.583,
            "operating profit": 374.302,
            "pre tax-profit": 402.105
        },
        {
            "date": "2017-12-31",
            "Year": 30,
            "ebitda": 559.939,
            "operating expenses": 3010.452,
            "cost of-sales": 2555.413,
            "net income": 56.159,
            "gross profit-on-sales": 815.26,
            "ebit": 441.83,
            "operating profit": 360.221,
            "pre tax-profit": 377.144
        },
        {
            "date": "2018-03-31",
            "Year": 31,
            "ebitda": 674.43,
            "operating expenses": 3279.764,
            "cost of-sales": 2815.497,
            "net income": 365.989,
            "gross profit-on-sales": 934.094,
            "ebit": 557.33,
            "operating profit": 469.827,
            "pre tax-profit": 487.285
        },
        {
            "date": "2018-06-30",
            "Year": 32,
            "ebitda": 759.288,
            "operating expenses": 3319.55,
            "cost of-sales": 2823.219,
            "net income": 353.256,
            "gross profit-on-sales": 994.258,
            "ebit": 644.519,
            "operating profit": 497.927,
            "pre tax-profit": 524.062
        },
        {
            "date": "2018-09-30",
            "Year": 33,
            "ebitda": 625.1432,
            "operating expenses": 3019.571,
            "cost of-sales": 2590.424,
            "net income": 375.711,
            "gross profit-on-sales": 888.87,
            "ebit": 512.6522,
            "operating profit": 459.723,
            "pre tax-profit": 468.336
        },
        {
            "date": "2018-12-31",
            "Year": 34,
            "ebitda": 578.726,
            "operating expenses": 3040.891,
            "cost of-sales": 2598.67,
            "net income": 311.737,
            "gross profit-on-sales": 873.375,
            "ebit": 468.674,
            "operating profit": 431.154,
            "pre tax-profit": 438.756
        },
        {
            "date": "2019-03-31",
            "Year": 35,
            "ebitda": 668.966,
            "operating expenses": 3158.318,
            "cost of-sales": 2763.94,
            "net income": 411.248,
            "gross profit-on-sales": 923.578,
            "ebit": 560.708,
            "operating profit": 529.2,
            "pre tax-profit": 533.799
        },
        {
            "date": "2019-06-30",
            "Year": 36,
            "ebitda": 656.009,
            "operating expenses": 3168.119,
            "cost of-sales": 2735.8,
            "net income": 413.668,
            "gross profit-on-sales": 945.667,
            "ebit": 550.621,
            "operating profit": 513.348,
            "pre tax-profit": 537.815
        },
        {
            "date": "2019-09-30",
            "Year": 37,
            "ebitda": 564.906,
            "operating expenses": 2901.355,
            "cost of-sales": 2476.396,
            "net income": 338.898,
            "gross profit-on-sales": 858.115,
            "ebit": 455.835,
            "operating profit": 433.156,
            "pre tax-profit": 459.337
        },
        {
            "date": "2019-12-31",
            "Year": 38,
            "ebitda": 468.702,
            "operating expenses": 3243.228,
            "cost of-sales": 2675.086,
            "net income": 204.474,
            "gross profit-on-sales": 822.888,
            "ebit": 324.473,
            "operating profit": 254.746,
            "pre tax-profit": 420.263
        },
        {
            "date": "2020-03-31",
            "Year": 39,
            "ebitda": 659.025,
            "operating expenses": 3248.275,
            "cost of-sales": 2756.492,
            "net income": 367.253,
            "gross profit-on-sales": 945.94,
            "ebit": 521.376,
            "operating profit": 454.157,
            "pre tax-profit": 494.626
        },
        {
            "date": "2020-06-30",
            "Year": 40,
            "ebitda": 633.073,
            "operating expenses": 2790.035,
            "cost of-sales": 2319.753,
            "net income": 295.716,
            "gross profit-on-sales": 840.85,
            "ebit": 486.491,
            "operating profit": 370.568,
            "pre tax-profit": 425.11
        },
        {
            "date": "2020-09-30",
            "Year": 41,
            "ebitda": 645.385,
            "operating expenses": 2815.245,
            "cost of-sales": 2372.178,
            "net income": 321.409,
            "gross profit-on-sales": 858.362,
            "ebit": 496.943,
            "operating profit": 415.295,
            "pre tax-profit": 516.646
        },
        {
            "date": "2020-12-31",
            "Year": 42,
            "ebitda": 807.971,
            "operating expenses": 2835.393,
            "cost of-sales": 2505.362,
            "net income": 447.306,
            "gross profit-on-sales": 906.543,
            "ebit": 658.153,
            "operating profit": 576.512,
            "pre tax-profit": 579.215
        },
        {
            "date": "2021-03-31",
            "Year": 43,
            "ebitda": 802.859,
            "operating expenses": 3099.617,
            "cost of-sales": 2709.729,
            "net income": 473.153,
            "gross profit-on-sales": 1036.597,
            "ebit": 652.311,
            "operating profit": 646.709,
            "pre tax-profit": 686.862
        },
        {
            "date": "2021-06-30",
            "Year": 44,
            "ebitda": 868.161,
            "operating expenses": 3245.082,
            "cost of-sales": 2826.677,
            "net income": 505.738,
            "gross profit-on-sales": 1132.192,
            "ebit": 721.579,
            "operating profit": 713.787,
            "pre tax-profit": 750.893
        },
        {
            "date": "2021-09-30",
            "Year": 45,
            "ebitda": 789.912,
            "operating expenses": 3160.662,
            "cost of-sales": 2712.896,
            "net income": 451.157,
            "gross profit-on-sales": 1049.913,
            "ebit": 644.161,
            "operating profit": 602.147,
            "pre tax-profit": 707.931
        },
        {
            "date": "2021-12-31",
            "Year": 46,
            "ebitda": 827.152,
            "operating expenses": 3155.435,
            "cost of-sales": 2763.015,
            "net income": 387.6,
            "gross profit-on-sales": 1061.565,
            "ebit": 682.79,
            "operating profit": 669.145,
            "pre tax-profit": 741.861
        },
        {
            "date": "2022-03-31",
            "Year": 47,
            "ebitda": 891.751,
            "operating expenses": 3349.485,
            "cost of-sales": 2926.234,
            "net income": 348.017,
            "gross profit-on-sales": 1160.153,
            "ebit": 749.054,
            "operating profit": 736.902,
            "pre tax-profit": 796.703
        },
        {
            "date": "2022-06-30",
            "Year": 48,
            "ebitda": 935.793,
            "operating expenses": 3423.867,
            "cost of-sales": 2977.301,
            "net income": 128.831,
            "gross profit-on-sales": 1210.531,
            "ebit": 795.974,
            "operating profit": 763.965,
            "pre tax-profit": 832.734
        },
        {
            "date": "2022-09-30",
            "Year": 49,
            "ebitda": 868.357,
            "operating expenses": 3631.26,
            "cost of-sales": 2792.957,
            "net income": 387.854,
            "gross profit-on-sales": 1439.818,
            "ebit": 714.376,
            "operating profit": 601.515,
            "pre tax-profit": 801.889
        },
        {
            "date": "2022-12-31",
            "Year": 50,
            "ebitda": 860.155,
            "operating expenses": 4051.778,
            "cost of-sales": 3233.598,
            "net income": 395.237,
            "gross profit-on-sales": 1441.213,
            "ebit": 630.411,
            "operating profit": 623.033,
            "pre tax-profit": 516.743
        },
        {
            "date": "2023-03-31",
            "Year": 51,
            "ebitda": 1087.09,
            "operating expenses": 4209.157,
            "cost of-sales": 3335.731,
            "net income": 590.889,
            "gross profit-on-sales": 1725.934,
            "ebit": 861.749,
            "operating profit": 852.508,
            "pre tax-profit": 990.881
        },
        {
            "date": "2023-06-30",
            "Year": 52,
            "ebitda": 1238.635,
            "operating expenses": 4103.274,
            "cost of-sales": 3257.613,
            "net income": 708.956,
            "gross profit-on-sales": 1838.33,
            "ebit": 1029.155,
            "operating profit": 992.669,
            "pre tax-profit": 1012.264
        },
        {
            "date": "2023-09-30",
            "Year": 53,
            "ebitda": 1136.824,
            "operating expenses": 3959.04,
            "cost of-sales": 3090.365,
            "net income": 650.827,
            "gross profit-on-sales": 1757.123,
            "ebit": 895.957,
            "operating profit": 888.448,
            "pre tax-profit": 982.193
        },
        {
            "date": "2023-12-31",
            "Year": 54,
            "ebitda": 1164.329,
            "operating expenses": 3908.764,
            "cost of-sales": 3101.962,
            "net income": 681.851,
            "gross profit-on-sales": 1718.985,
            "ebit": 936.551,
            "operating profit": 912.183,
            "pre tax-profit": 868.165
        },
        {
            "date": "2024-03-31",
            "Year": 55,
            "ebitda": 1272.073,
            "operating expenses": 4077.987,
            "cost of-sales": 3279.65,
            "net income": 726.574,
            "gross profit-on-sales": 1794.706,
            "ebit": 1043.775,
            "operating profit": 996.369,
            "pre tax-profit": 920.043
        },
        {
            "date": "2024-06-30",
            "Year": 56,
            "ebitda": 1335.894,
            "operating expenses": 4141.2,
            "cost of-sales": 3322.86,
            "net income": 784.96,
            "gross profit-on-sales": 1863.96,
            "ebit": 1105.226,
            "operating profit": 1045.61,
            "pre tax-profit": 985.96
        },
        {
            "date": "2024-09-30",
            "Year": 57,
            "ebitda": 1191.978,
            "operating expenses": 3946.508,
            "cost of-sales": 3097.719,
            "net income": 698.42,
            "gross profit-on-sales": 1806.265,
            "ebit": 1112.916,
            "operating profit": 957.476,
            "pre tax-profit": 875.19
        },
        {
            "date": "2024-12-31",
            "Year": 58,
            "ebitda": 941.766,
            "operating expenses": 3804.65,
            "cost of-sales": 3022.229,
            "net income": 948.542,
            "gross profit-on-sales": 1720.364,
            "ebit": 1103.817,
            "operating profit": 937.943,
            "pre tax-profit": 1165.86
        }
    ]
}