{
    "company_code": "SNX",
    "financial_data": [
        {
            "date": "2004-11-30",
            "Year": 0,
            "ebitda": 25.166,
            "operating expenses": 1417705000.0,
            "cost of-sales": 1379.555,
            "net income": 15.252,
            "gross profit-on-sales": 61.26,
            "ebit": 21516000.0,
            "operating profit": 23.11,
            "pre tax-profit": 18.01
        },
        {
            "date": "2005-02-28",
            "Year": 1,
            "ebitda": 18.645,
            "operating expenses": 1293341000.0,
            "cost of-sales": 1253.629,
            "net income": 8.607,
            "gross profit-on-sales": 56.134,
            "ebit": 18728000.0,
            "operating profit": 16.422,
            "pre tax-profit": 16.283
        },
        {
            "date": "2005-05-31",
            "Year": 2,
            "ebitda": 20.562,
            "operating expenses": 1327931000.0,
            "cost of-sales": 1289.772,
            "net income": 22.381,
            "gross profit-on-sales": 56.556,
            "ebit": 18397000.0,
            "operating profit": 18.397,
            "pre tax-profit": 15.877
        },
        {
            "date": "2005-08-31",
            "Year": 3,
            "ebitda": 21.941,
            "operating expenses": 1371861000.0,
            "cost of-sales": 1332.612,
            "net income": 9.038,
            "gross profit-on-sales": 58.978,
            "ebit": 20571000.0,
            "operating profit": 19.729,
            "pre tax-profit": 17.265
        },
        {
            "date": "2005-11-30",
            "Year": 4,
            "ebitda": 26.539,
            "operating expenses": 1568699000.0,
            "cost of-sales": 1526.198,
            "net income": 12.799,
            "gross profit-on-sales": 66.89,
            "ebit": 24999000.0,
            "operating profit": 24.389,
            "pre tax-profit": 19.519
        },
        {
            "date": "2006-02-28",
            "Year": 5,
            "ebitda": 24.486,
            "operating expenses": 1479488000.0,
            "cost of-sales": 1436.725,
            "net income": 10.683,
            "gross profit-on-sales": 65.01,
            "ebit": 22200000.0,
            "operating profit": 22.247,
            "pre tax-profit": 16.667
        },
        {
            "date": "2006-05-31",
            "Year": 6,
            "ebitda": 24.713,
            "operating expenses": 1489305000.0,
            "cost of-sales": 1443.353,
            "net income": 11.317,
            "gross profit-on-sales": 68.348,
            "ebit": 22396000.0,
            "operating profit": 22.396,
            "pre tax-profit": 17.574
        },
        {
            "date": "2006-08-31",
            "Year": 7,
            "ebitda": 25.982,
            "operating expenses": 1568691000.0,
            "cost of-sales": 1519.486,
            "net income": 13.779,
            "gross profit-on-sales": 72.718,
            "ebit": 23513000.0,
            "operating profit": 23.513,
            "pre tax-profit": 21.035
        },
        {
            "date": "2006-11-30",
            "Year": 8,
            "ebitda": 30.842,
            "operating expenses": 1709788000.0,
            "cost of-sales": 1658.591,
            "net income": 15.606,
            "gross profit-on-sales": 79.283,
            "ebit": 28086000.0,
            "operating profit": 28.086,
            "pre tax-profit": 24.877
        },
        {
            "date": "2007-02-28",
            "Year": 9,
            "ebitda": 27.775,
            "operating expenses": 1563333000.0,
            "cost of-sales": 1513.852,
            "net income": 13.875,
            "gross profit-on-sales": 74.424,
            "ebit": 24943000.0,
            "operating profit": 24.943,
            "pre tax-profit": 22.043
        },
        {
            "date": "2007-05-31",
            "Year": 10,
            "ebitda": 29.977,
            "operating expenses": 1658996000.0,
            "cost of-sales": 1600.563,
            "net income": 14.671,
            "gross profit-on-sales": 84.245,
            "ebit": 25812000.0,
            "operating profit": 25.812,
            "pre tax-profit": 23.021
        },
        {
            "date": "2007-08-31",
            "Year": 11,
            "ebitda": 31.531,
            "operating expenses": 1735838000.0,
            "cost of-sales": 1669.134,
            "net income": 14.396,
            "gross profit-on-sales": 91.226,
            "ebit": 27266000.0,
            "operating profit": 24.522,
            "pre tax-profit": 23.662
        },
        {
            "date": "2007-11-30",
            "Year": 12,
            "ebitda": 41.238,
            "operating expenses": 1933806000.0,
            "cost of-sales": 1865.189,
            "net income": 20.185,
            "gross profit-on-sales": 105.487,
            "ebit": 36870000.0,
            "operating profit": 36.87,
            "pre tax-profit": 32.684
        },
        {
            "date": "2008-02-29",
            "Year": 13,
            "ebitda": 35.912,
            "operating expenses": 1710254000.0,
            "cost of-sales": 1649.714,
            "net income": 16.828,
            "gross profit-on-sales": 92.064,
            "ebit": 32780000.0,
            "operating profit": 31.524,
            "pre tax-profit": 26.567
        },
        {
            "date": "2008-05-31",
            "Year": 14,
            "ebitda": 34.857,
            "operating expenses": 1839736000.0,
            "cost of-sales": 1773.765,
            "net income": 18.511,
            "gross profit-on-sales": 96.086,
            "ebit": 31672000.0,
            "operating profit": 30.115,
            "pre tax-profit": 28.943
        },
        {
            "date": "2008-08-31",
            "Year": 15,
            "ebitda": 43.178,
            "operating expenses": 1999280000.0,
            "cost of-sales": 1929.344,
            "net income": 22.06,
            "gross profit-on-sales": 108.149,
            "ebit": 39505000.0,
            "operating profit": 38.213,
            "pre tax-profit": 34.581
        },
        {
            "date": "2008-11-30",
            "Year": 16,
            "ebitda": 51.183,
            "operating expenses": 2041090000.0,
            "cost of-sales": 1970.039,
            "net income": 26.398,
            "gross profit-on-sales": 117.565,
            "ebit": 47891000.0,
            "operating profit": 46.514,
            "pre tax-profit": 39.495
        },
        {
            "date": "2009-02-28",
            "Year": 17,
            "ebitda": 38.878,
            "operating expenses": 1686583000.0,
            "cost of-sales": 1619.523,
            "net income": 18.891,
            "gross profit-on-sales": 100.847,
            "ebit": 34700000.0,
            "operating profit": 33.787,
            "pre tax-profit": 30.31
        },
        {
            "date": "2009-05-31",
            "Year": 18,
            "ebitda": 34.909,
            "operating expenses": 1772712000.0,
            "cost of-sales": 1701.765,
            "net income": 18.633,
            "gross profit-on-sales": 100.94,
            "ebit": 31698000.0,
            "operating profit": 29.993,
            "pre tax-profit": 30.045
        },
        {
            "date": "2009-08-31",
            "Year": 19,
            "ebitda": 43.328,
            "operating expenses": 1959861000.0,
            "cost of-sales": 1892.083,
            "net income": 22.465,
            "gross profit-on-sales": 105.977,
            "ebit": 31698000.0,
            "operating profit": 38.199,
            "pre tax-profit": 36.911
        },
        {
            "date": "2009-11-30",
            "Year": 20,
            "ebitda": 51.446,
            "operating expenses": 2150392000.0,
            "cost of-sales": 2082.796,
            "net income": 29.678,
            "gross profit-on-sales": 115.266,
            "ebit": 47671000.0,
            "operating profit": 47.67,
            "pre tax-profit": 45.454
        },
        {
            "date": "2010-02-28",
            "Year": 21,
            "ebitda": 42.987,
            "operating expenses": 1897085000.0,
            "cost of-sales": 1826.877,
            "net income": 34.659,
            "gross profit-on-sales": 109.161,
            "ebit": 39000000.0,
            "operating profit": 38.953,
            "pre tax-profit": 36.307
        },
        {
            "date": "2010-05-31",
            "Year": 22,
            "ebitda": 47.689,
            "operating expenses": 1989378000.0,
            "cost of-sales": 1916.145,
            "net income": 24.844,
            "gross profit-on-sales": 116.667,
            "ebit": 35776000.0,
            "operating profit": 43.434,
            "pre tax-profit": 39.605
        },
        {
            "date": "2010-08-31",
            "Year": 23,
            "ebitda": 56.519,
            "operating expenses": 2124912000.0,
            "cost of-sales": 2052.197,
            "net income": 30.914,
            "gross profit-on-sales": 124.869,
            "ebit": 52154000.0,
            "operating profit": 52.154,
            "pre tax-profit": 47.269
        },
        {
            "date": "2010-11-30",
            "Year": 24,
            "ebitda": 68.571,
            "operating expenses": 2403616000.0,
            "cost of-sales": 2327.306,
            "net income": 37.531,
            "gross profit-on-sales": 140.919,
            "ebit": 64609000.0,
            "operating profit": 64.609,
            "pre tax-profit": 60.405
        },
        {
            "date": "2011-02-28",
            "Year": 25,
            "ebitda": 57.908,
            "operating expenses": 2450081000.0,
            "cost of-sales": 2357.138,
            "net income": 29.721,
            "gross profit-on-sales": 143.796,
            "ebit": 51582000.0,
            "operating profit": 50.853,
            "pre tax-profit": 46.378
        },
        {
            "date": "2011-05-31",
            "Year": 26,
            "ebitda": 60.535,
            "operating expenses": 2441642000.0,
            "cost of-sales": 2350.694,
            "net income": 31.401,
            "gross profit-on-sales": 145.108,
            "ebit": 54562000.0,
            "operating profit": 54.16,
            "pre tax-profit": 48.473
        },
        {
            "date": "2011-08-31",
            "Year": 27,
            "ebitda": 72.045,
            "operating expenses": 2505615000.0,
            "cost of-sales": 2418.38,
            "net income": 39.036,
            "gross profit-on-sales": 153.753,
            "ebit": 62418000.0,
            "operating profit": 66.518,
            "pre tax-profit": 54.732
        },
        {
            "date": "2011-11-30",
            "Year": 28,
            "ebitda": 91.742,
            "operating expenses": 2756274000.0,
            "cost of-sales": 2653.13,
            "net income": 50.173,
            "gross profit-on-sales": 187.841,
            "ebit": 84697000.0,
            "operating profit": 84.697,
            "pre tax-profit": 77.166
        },
        {
            "date": "2012-02-29",
            "Year": 29,
            "ebitda": 70.104,
            "operating expenses": 2396706000.0,
            "cost of-sales": 2291.422,
            "net income": 38.223,
            "gross profit-on-sales": 169.272,
            "ebit": 63988000.0,
            "operating profit": 63.988,
            "pre tax-profit": 60.052
        },
        {
            "date": "2012-05-31",
            "Year": 30,
            "ebitda": 65.592,
            "operating expenses": 2423478000.0,
            "cost of-sales": 2326.363,
            "net income": 34.374,
            "gross profit-on-sales": 156.436,
            "ebit": 59321000.0,
            "operating profit": 59.321,
            "pre tax-profit": 53.42
        },
        {
            "date": "2012-08-31",
            "Year": 31,
            "ebitda": 63.318,
            "operating expenses": 2519897000.0,
            "cost of-sales": 2425.019,
            "net income": 35.139,
            "gross profit-on-sales": 151.929,
            "ebit": 57051000.0,
            "operating profit": 57.051,
            "pre tax-profit": 52.132
        },
        {
            "date": "2012-11-30",
            "Year": 32,
            "ebitda": 91.128,
            "operating expenses": 2690414000.0,
            "cost of-sales": 2585.966,
            "net income": 43.64,
            "gross profit-on-sales": 179.1,
            "ebit": 74652000.0,
            "operating profit": 74.652,
            "pre tax-profit": 70.949
        },
        {
            "date": "2013-02-28",
            "Year": 33,
            "ebitda": 62.168,
            "operating expenses": 2404899000.0,
            "cost of-sales": 2304.752,
            "net income": 33.369,
            "gross profit-on-sales": 156.087,
            "ebit": 55940000.0,
            "operating profit": 55.94,
            "pre tax-profit": 51.708
        },
        {
            "date": "2013-05-31",
            "Year": 34,
            "ebitda": 57.929,
            "operating expenses": 2539397000.0,
            "cost of-sales": 2436.571,
            "net income": 30.769,
            "gross profit-on-sales": 154.79,
            "ebit": 54064000.0,
            "operating profit": 51.964,
            "pre tax-profit": 49.729
        },
        {
            "date": "2013-08-31",
            "Year": 35,
            "ebitda": 69.558,
            "operating expenses": 2670414000.0,
            "cost of-sales": 2569.633,
            "net income": 46.611,
            "gross profit-on-sales": 164.28,
            "ebit": 63499000.0,
            "operating profit": 63.499,
            "pre tax-profit": 112.149
        },
        {
            "date": "2013-11-30",
            "Year": 36,
            "ebitda": 83.135,
            "operating expenses": 2989626000.0,
            "cost of-sales": 2879.238,
            "net income": 41.488,
            "gross profit-on-sales": 179.813,
            "ebit": 75223000.0,
            "operating profit": 69.425,
            "pre tax-profit": 71.862
        },
        {
            "date": "2014-02-28",
            "Year": 37,
            "ebitda": 82.212,
            "operating expenses": 2965034000.0,
            "cost of-sales": 2820.338,
            "net income": 38.417,
            "gross profit-on-sales": 206.646,
            "ebit": 76555000.0,
            "operating profit": 61.95,
            "pre tax-profit": 75.025
        },
        {
            "date": "2014-05-31",
            "Year": 38,
            "ebitda": 108.148,
            "operating expenses": 3385452000.0,
            "cost of-sales": 3174.521,
            "net income": 39.551,
            "gross profit-on-sales": 279.014,
            "ebit": 98990000.0,
            "operating profit": 68.083,
            "pre tax-profit": 92.633
        },
        {
            "date": "2014-08-31",
            "Year": 39,
            "ebitda": 106.68,
            "operating expenses": 3456400000.0,
            "cost of-sales": 3235.48,
            "net income": 44.986,
            "gross profit-on-sales": 299.722,
            "ebit": 106298000.0,
            "operating profit": 78.802,
            "pre tax-profit": 98.148
        },
        {
            "date": "2014-11-30",
            "Year": 40,
            "ebitda": 170.944,
            "operating expenses": 3724197000.0,
            "cost of-sales": 3510.247,
            "net income": 57.08,
            "gross profit-on-sales": 313.622,
            "ebit": 124861000.0,
            "operating profit": 99.672,
            "pre tax-profit": 116.673
        },
        {
            "date": "2015-02-28",
            "Year": 41,
            "ebitda": 108.711,
            "operating expenses": 3123511000.0,
            "cost of-sales": 2914.24,
            "net income": 46.323,
            "gross profit-on-sales": 288.218,
            "ebit": 97533000.0,
            "operating profit": 78.947,
            "pre tax-profit": 91.159
        },
        {
            "date": "2015-05-31",
            "Year": 42,
            "ebitda": 115.932,
            "operating expenses": 3164424000.0,
            "cost of-sales": 2953.726,
            "net income": 51.874,
            "gross profit-on-sales": 300.059,
            "ebit": 104862000.0,
            "operating profit": 89.361,
            "pre tax-profit": 97.463
        },
        {
            "date": "2015-08-31",
            "Year": 43,
            "ebitda": 108.02,
            "operating expenses": 3251258000.0,
            "cost of-sales": 3041.759,
            "net income": 48.171,
            "gross profit-on-sales": 290.778,
            "ebit": 97034000.0,
            "operating profit": 81.279,
            "pre tax-profit": 90.09
        },
        {
            "date": "2015-11-30",
            "Year": 44,
            "ebitda": 141.508,
            "operating expenses": 3444652000.0,
            "cost of-sales": 3236.881,
            "net income": 62.157,
            "gross profit-on-sales": 312.736,
            "ebit": 119988000.0,
            "operating profit": 104.965,
            "pre tax-profit": 113.348
        },
        {
            "date": "2016-02-29",
            "Year": 45,
            "ebitda": 101.804,
            "operating expenses": 3049996000.0,
            "cost of-sales": 2841.43,
            "net income": 46.562,
            "gross profit-on-sales": 284.192,
            "ebit": 88322000.0,
            "operating profit": 75.626,
            "pre tax-profit": 80.925
        },
        {
            "date": "2016-05-31",
            "Year": 46,
            "ebitda": 103.8,
            "operating expenses": 3304193000.0,
            "cost of-sales": 3085.469,
            "net income": 44.362,
            "gross profit-on-sales": 294.03,
            "ebit": 91665000.0,
            "operating profit": 75.306,
            "pre tax-profit": 85.44
        },
        {
            "date": "2016-08-31",
            "Year": 47,
            "ebitda": 126.408,
            "operating expenses": 3571792000.0,
            "cost of-sales": 3343.857,
            "net income": 58.704,
            "gross profit-on-sales": 325.957,
            "ebit": 113649000.0,
            "operating profit": 98.022,
            "pre tax-profit": 105.593
        },
        {
            "date": "2016-11-30",
            "Year": 48,
            "ebitda": 170.083,
            "operating expenses": 3756260000.0,
            "cost of-sales": 3508.116,
            "net income": 85.318,
            "gross profit-on-sales": 378.786,
            "ebit": 156088000.0,
            "operating profit": 130.642,
            "pre tax-profit": 148.196
        },
        {
            "date": "2017-02-28",
            "Year": 49,
            "ebitda": 138.317,
            "operating expenses": 3419110000.0,
            "cost of-sales": 3179.086,
            "net income": 61.789,
            "gross profit-on-sales": 341.783,
            "ebit": 118857000.0,
            "operating profit": 101.759,
            "pre tax-profit": 110.352
        },
        {
            "date": "2017-05-31",
            "Year": 50,
            "ebitda": 160.612,
            "operating expenses": 3811138000.0,
            "cost of-sales": 3564.023,
            "net income": 73.148,
            "gross profit-on-sales": 372.245,
            "ebit": 141199000.0,
            "operating profit": 125.13,
            "pre tax-profit": 132.031
        },
        {
            "date": "2017-08-31",
            "Year": 51,
            "ebitda": 160.115,
            "operating expenses": 4154470000.0,
            "cost of-sales": 3901.742,
            "net income": 75.163,
            "gross profit-on-sales": 374.944,
            "ebit": 139930000.0,
            "operating profit": 122.216,
            "pre tax-profit": 132.03
        },
        {
            "date": "2017-11-30",
            "Year": 52,
            "ebitda": 209.816,
            "operating expenses": 4879073000.0,
            "cost of-sales": 4576.965,
            "net income": 90.14,
            "gross profit-on-sales": 460.34,
            "ebit": 192941000.0,
            "operating profit": 158.232,
            "pre tax-profit": 173.975
        },
        {
            "date": "2018-02-28",
            "Year": 53,
            "ebitda": 161.935,
            "operating expenses": 4381854000.0,
            "cost of-sales": 4079.835,
            "net income": 24.098,
            "gross profit-on-sales": 413.515,
            "ebit": 140447000.0,
            "operating profit": 111.496,
            "pre tax-profit": 121.221
        },
        {
            "date": "2018-05-31",
            "Year": 54,
            "ebitda": 174.92,
            "operating expenses": 4784279000.0,
            "cost of-sales": 4479.123,
            "net income": 93.742,
            "gross profit-on-sales": 429.158,
            "ebit": 152300000.0,
            "operating profit": 124.002,
            "pre tax-profit": 131.805
        },
        {
            "date": "2018-08-31",
            "Year": 55,
            "ebitda": 182.119,
            "operating expenses": 4708425000.0,
            "cost of-sales": 4392.151,
            "net income": 66.94,
            "gross profit-on-sales": 430.117,
            "ebit": 162661000.0,
            "operating profit": 113.843,
            "pre tax-profit": 141.731
        },
        {
            "date": "2018-11-30",
            "Year": 56,
            "ebitda": 301.681,
            "operating expenses": 5343152000.0,
            "cost of-sales": 4889.937,
            "net income": 115.202,
            "gross profit-on-sales": 654.11,
            "ebit": 265132000.0,
            "operating profit": 200.895,
            "pre tax-profit": 228.854
        },
        {
            "date": "2019-02-28",
            "Year": 57,
            "ebitda": 283.854,
            "operating expenses": 5087490000.0,
            "cost of-sales": 4570.532,
            "net income": 87.106,
            "gross profit-on-sales": 678.921,
            "ebit": 242669000.0,
            "operating profit": 161.963,
            "pre tax-profit": 199.638
        },
        {
            "date": "2019-05-31",
            "Year": 58,
            "ebitda": 285.834,
            "operating expenses": 5548234000.0,
            "cost of-sales": 5024.42,
            "net income": 114.473,
            "gross profit-on-sales": 698.469,
            "ebit": 244052000.0,
            "operating profit": 174.655,
            "pre tax-profit": 203.249
        },
        {
            "date": "2019-08-31",
            "Year": 59,
            "ebitda": 309.608,
            "operating expenses": 5994804000.0,
            "cost of-sales": 5477.669,
            "net income": 123.132,
            "gross profit-on-sales": 725.99,
            "ebit": 270483000.0,
            "operating profit": 208.855,
            "pre tax-profit": 225.919
        },
        {
            "date": "2019-11-30",
            "Year": 60,
            "ebitda": 378.027,
            "operating expenses": 6313005000.0,
            "cost of-sales": 5786.753,
            "net income": 176.001,
            "gross profit-on-sales": 794.54,
            "ebit": 338492000.0,
            "operating profit": 268.288,
            "pre tax-profit": 299.253
        },
        {
            "date": "2020-02-29",
            "Year": 61,
            "ebitda": 116.788,
            "operating expenses": 3980579000.0,
            "cost of-sales": 3825.92,
            "net income": 122.585,
            "gross profit-on-sales": 255.104,
            "ebit": 250891000.0,
            "operating profit": 100.445,
            "pre tax-profit": 216.473
        },
        {
            "date": "2020-05-31",
            "Year": 62,
            "ebitda": 103.991,
            "operating expenses": 4382784000.0,
            "cost of-sales": 4196.312,
            "net income": 56.96,
            "gross profit-on-sales": 274.616,
            "ebit": 161518000.0,
            "operating profit": 88.144,
            "pre tax-profit": 129.3
        },
        {
            "date": "2020-08-31",
            "Year": 63,
            "ebitda": 149.583,
            "operating expenses": 5173988000.0,
            "cost of-sales": 5008.881,
            "net income": 134.464,
            "gross profit-on-sales": 297.48,
            "ebit": 260127000.0,
            "operating profit": 132.373,
            "pre tax-profit": 230.248
        },
        {
            "date": "2020-11-30",
            "Year": 64,
            "ebitda": 296.339,
            "operating expenses": 5918458000.0,
            "cost of-sales": 5752.179,
            "net income": 215.151,
            "gross profit-on-sales": 366.658,
            "ebit": 388245000.0,
            "operating profit": 200.379,
            "pre tax-profit": 357.951
        },
        {
            "date": "2021-02-28",
            "Year": 65,
            "ebitda": 157.363,
            "operating expenses": 4797266000.0,
            "cost of-sales": 4634.447,
            "net income": 87.822,
            "gross profit-on-sales": 304.567,
            "ebit": 156004000.0,
            "operating profit": 141.748,
            "pre tax-profit": 131.686
        },
        {
            "date": "2021-05-31",
            "Year": 66,
            "ebitda": 169.722,
            "operating expenses": 5708924000.0,
            "cost of-sales": 5527.65,
            "net income": 93.102,
            "gross profit-on-sales": 329.175,
            "ebit": 169959000.0,
            "operating profit": 147.901,
            "pre tax-profit": 146.363
        },
        {
            "date": "2021-08-31",
            "Year": 67,
            "ebitda": 170.756,
            "operating expenses": 5058860000.0,
            "cost of-sales": 4894.442,
            "net income": 94.704,
            "gross profit-on-sales": 312.622,
            "ebit": 168232000.0,
            "operating profit": 148.204,
            "pre tax-profit": 149.5
        },
        {
            "date": "2021-11-30",
            "Year": 68,
            "ebitda": 389.192,
            "operating expenses": 15425900000.0,
            "cost of-sales": 14668.096,
            "net income": 119.44,
            "gross profit-on-sales": 943.169,
            "ebit": 407936000.0,
            "operating profit": 185.365,
            "pre tax-profit": 362.256
        },
        {
            "date": "2022-02-28",
            "Year": 69,
            "ebitda": 471.311,
            "operating expenses": 15247537000.0,
            "cost of-sales": 14501.316,
            "net income": 132.324,
            "gross profit-on-sales": 968.661,
            "ebit": 431857000.0,
            "operating profit": 222.44,
            "pre tax-profit": 353.917
        },
        {
            "date": "2022-05-31",
            "Year": 70,
            "ebitda": 384.84,
            "operating expenses": 15017054000.0,
            "cost of-sales": 14314.002,
            "net income": 148.917,
            "gross profit-on-sales": 955.789,
            "ebit": 398321000.0,
            "operating profit": 252.737,
            "pre tax-profit": 344.098
        },
        {
            "date": "2022-08-31",
            "Year": 71,
            "ebitda": 389.469,
            "operating expenses": 15114551000.0,
            "cost of-sales": 14440.055,
            "net income": 148.835,
            "gross profit-on-sales": 916.03,
            "ebit": 398283000.0,
            "operating profit": 241.534,
            "pre tax-profit": 302.152
        },
        {
            "date": "2022-11-30",
            "Year": 72,
            "ebitda": 490.937,
            "operating expenses": 15913795000.0,
            "cost of-sales": 15188.238,
            "net income": 221.231,
            "gross profit-on-sales": 1059.719,
            "ebit": 495578000.0,
            "operating profit": 334.162,
            "pre tax-profit": 428.904
        },
        {
            "date": "2023-02-28",
            "Year": 73,
            "ebitda": 456.264,
            "operating expenses": 14827209000.0,
            "cost of-sales": 14121.804,
            "net income": 167.02,
            "gross profit-on-sales": 1003.567,
            "ebit": 442891000.0,
            "operating profit": 298.162,
            "pre tax-profit": 364.777
        },
        {
            "date": "2023-05-31",
            "Year": 74,
            "ebitda": 396.962,
            "operating expenses": 13809241000.0,
            "cost of-sales": 13098.714,
            "net income": 133.087,
            "gross profit-on-sales": 963.41,
            "ebit": 376049000.0,
            "operating profit": 252.883,
            "pre tax-profit": 299.896
        },
        {
            "date": "2023-08-31",
            "Year": 75,
            "ebitda": 419.415,
            "operating expenses": 13720382000.0,
            "cost of-sales": 12989.342,
            "net income": 139.262,
            "gross profit-on-sales": 971.273,
            "ebit": 396800000.0,
            "operating profit": 240.233,
            "pre tax-profit": 329.042
        },
        {
            "date": "2023-11-30",
            "Year": 76,
            "ebitda": 437.291,
            "operating expenses": 14120552000.0,
            "cost of-sales": 13388.727,
            "net income": 187.542,
            "gross profit-on-sales": 1018.579,
            "ebit": 426579000.0,
            "operating profit": 286.754,
            "pre tax-profit": 367.435
        },
        {
            "date": "2024-02-29",
            "Year": 77,
            "ebitda": 434.84,
            "operating expenses": 13672681000.0,
            "cost of-sales": 12969.487,
            "net income": 172.128,
            "gross profit-on-sales": 1005.766,
            "ebit": 424588000.0,
            "operating profit": 302.572,
            "pre tax-profit": 345.813
        },
        {
            "date": "2024-05-31",
            "Year": 78,
            "ebitda": 408.12,
            "operating expenses": 13683960000.0,
            "cost of-sales": 12974.361,
            "net income": 143.605,
            "gross profit-on-sales": 973.547,
            "ebit": 388022000.0,
            "operating profit": 263.948,
            "pre tax-profit": 308.23
        },
        {
            "date": "2024-08-31",
            "Year": 79,
            "ebitda": 401.723,
            "operating expenses": 14381833000.0,
            "cost of-sales": 13723.664,
            "net income": 178.556,
            "gross profit-on-sales": 961.048,
            "ebit": 392884000.0,
            "operating profit": 302.879,
            "pre tax-profit": 310.919
        },
        {
            "date": "2024-11-30",
            "Year": 80,
            "ebitda": 428.374,
            "operating expenses": 15519751000.0,
            "cost of-sales": 14803.618,
            "net income": 194.802,
            "gross profit-on-sales": 1040.945,
            "ebit": 421536000.0,
            "operating profit": 324.812,
            "pre tax-profit": 333.892
        }
    ]
}